htse/__init__.py
htse/_version.py
htse/_internal/molellipsize.py
htse/_internal/poremapper.py
htse/_internal/properties.py
htse/_internal/spindry.py
htse/_internal/utilities.py
htse/_internal/xtb.py
htse-2026.1.16.0.dist-info/licenses/LICENSE
htse-2026.1.16.0.dist-info/METADATA
htse-2026.1.16.0.dist-info/WHEEL
htse-2026.1.16.0.dist-info/top_level.txt
htse-2026.1.16.0.dist-info/RECORD
