Metadata-Version: 2.4
Name: htse
Version: 2026.1.16.0
Maintainer-email: Andrew Tarzia <andrew.tarzia@gmail.com>
Project-URL: github, https://github.com/andrewtarzia/HTSExclusion
Requires-Python: >=3.11
License-File: LICENSE
Requires-Dist: mol-ellipsize
Requires-Dist: PoreMapper
Requires-Dist: pywindowx
Requires-Dist: stko
Provides-Extra: dev
Requires-Dist: ruff; extra == "dev"
Requires-Dist: mypy; extra == "dev"
Requires-Dist: pytest<8; extra == "dev"
Requires-Dist: pytest-cov; extra == "dev"
Requires-Dist: sphinx; extra == "dev"
Requires-Dist: sphinx-copybutton; extra == "dev"
Requires-Dist: sphinx-rtd-theme; extra == "dev"
Requires-Dist: twine; extra == "dev"
Dynamic: license-file
